{"data":{"allBenchmarkSuite":{"nodes":[{"id":"21ee623c-b58a-5e67-85cd-83ae4fcfb378","name":"boolean","results":[{"component":"SERIALIZATION","iterations":10000000,"library":{"id":"66e268f2-4d8f-59f4-872d-58609fb3bbe5","name":"Confluent.Apache.Avro"},"times":[409.2206,339.1399,322.5898,317.4517,317.6478]},{"component":"DESERIALIZATION","iterations":10000000,"library":{"id":"66e268f2-4d8f-59f4-872d-58609fb3bbe5","name":"Confluent.Apache.Avro"},"times":[343.0323,204.9497,199.4167,197.0501,196.6818]},{"component":"SERIALIZATION","iterations":10000000,"library":{"id":"fc5220cb-3ca8-5528-84ff-663895a492cd","name":"Chr.Avro"},"times":[127.7925,123.0913,108.9941,98.1492,93.8811]},{"component":"DESERIALIZATION","iterations":10000000,"library":{"id":"fc5220cb-3ca8-5528-84ff-663895a492cd","name":"Chr.Avro"},"times":[81.9166,80.2914,66.5803,66.4168,66.1541]}]},{"id":"29791f9a-fc2e-53a7-acda-6cee736dacaa","name":"double","results":[{"component":"SERIALIZATION","iterations":10000000,"library":{"id":"66e268f2-4d8f-59f4-872d-58609fb3bbe5","name":"Confluent.Apache.Avro"},"times":[787.2828,768.0073,725.4088,712.6863,728.0418]},{"component":"DESERIALIZATION","iterations":10000000,"library":{"id":"66e268f2-4d8f-59f4-872d-58609fb3bbe5","name":"Confluent.Apache.Avro"},"times":[475.1559,391.0587,384.9458,387.4869,385.0033]},{"component":"SERIALIZATION","iterations":10000000,"library":{"id":"fc5220cb-3ca8-5528-84ff-663895a492cd","name":"Chr.Avro"},"times":[372.0246,372.6519,371.2154,377.3744,381.8712]},{"component":"DESERIALIZATION","iterations":10000000,"library":{"id":"fc5220cb-3ca8-5528-84ff-663895a492cd","name":"Chr.Avro"},"times":[280.9438,263.1573,269.6517,271.3615,272.686]}]},{"id":"28b66e0b-1538-55c9-86a3-b9e793a46f7e","name":"float","results":[{"component":"SERIALIZATION","iterations":10000000,"library":{"id":"66e268f2-4d8f-59f4-872d-58609fb3bbe5","name":"Confluent.Apache.Avro"},"times":[620.2606,569.8963,593.8834,592.3349,527.9402]},{"component":"DESERIALIZATION","iterations":10000000,"library":{"id":"66e268f2-4d8f-59f4-872d-58609fb3bbe5","name":"Confluent.Apache.Avro"},"times":[480.9137,427.0609,424.509,392.3629,444.274]},{"component":"SERIALIZATION","iterations":10000000,"library":{"id":"fc5220cb-3ca8-5528-84ff-663895a492cd","name":"Chr.Avro"},"times":[328.3774,308.3091,313.397,281.4711,300.5019]},{"component":"DESERIALIZATION","iterations":10000000,"library":{"id":"fc5220cb-3ca8-5528-84ff-663895a492cd","name":"Chr.Avro"},"times":[262.9694,237.0198,224.7821,221.1506,221.7896]}]},{"id":"e5e7e118-1f17-5211-8368-ee9eb8d780d6","name":"int","results":[{"component":"SERIALIZATION","iterations":10000000,"library":{"id":"66e268f2-4d8f-59f4-872d-58609fb3bbe5","name":"Confluent.Apache.Avro"},"times":[516.5579,481.1711,437.8586,442.9264,432.5723]},{"component":"DESERIALIZATION","iterations":10000000,"library":{"id":"66e268f2-4d8f-59f4-872d-58609fb3bbe5","name":"Confluent.Apache.Avro"},"times":[407.6494,338.8952,335.6781,336.1835,336.052]},{"component":"SERIALIZATION","iterations":10000000,"library":{"id":"fc5220cb-3ca8-5528-84ff-663895a492cd","name":"Chr.Avro"},"times":[213.5956,213.8564,193.1329,200.3002,194.9346]},{"component":"DESERIALIZATION","iterations":10000000,"library":{"id":"fc5220cb-3ca8-5528-84ff-663895a492cd","name":"Chr.Avro"},"times":[152.148,154.0478,150.0124,153.5138,164.1363]}]},{"id":"31cd8dd1-0fe5-5628-8fa4-1e473f63f9f7","name":"long","results":[{"component":"SERIALIZATION","iterations":10000000,"library":{"id":"66e268f2-4d8f-59f4-872d-58609fb3bbe5","name":"Confluent.Apache.Avro"},"times":[620.0253,631.2048,581.0652,604.5078,641.0592]},{"component":"DESERIALIZATION","iterations":10000000,"library":{"id":"66e268f2-4d8f-59f4-872d-58609fb3bbe5","name":"Confluent.Apache.Avro"},"times":[569.687,513.3229,584.0434,540.5965,535.7381]},{"component":"SERIALIZATION","iterations":10000000,"library":{"id":"fc5220cb-3ca8-5528-84ff-663895a492cd","name":"Chr.Avro"},"times":[329.6423,358.8749,346.7634,327.2653,318.9264]},{"component":"DESERIALIZATION","iterations":10000000,"library":{"id":"fc5220cb-3ca8-5528-84ff-663895a492cd","name":"Chr.Avro"},"times":[220.4865,226.0158,218.6872,232.1411,217.8865]}]},{"id":"89156835-6457-5abd-9a94-3070f057e003","name":"string","results":[{"component":"SERIALIZATION","iterations":10000000,"library":{"id":"66e268f2-4d8f-59f4-872d-58609fb3bbe5","name":"Confluent.Apache.Avro"},"times":[1228.8924,1504.3841,1307.8392,1246.3862,1248.6135]},{"component":"DESERIALIZATION","iterations":10000000,"library":{"id":"66e268f2-4d8f-59f4-872d-58609fb3bbe5","name":"Confluent.Apache.Avro"},"times":[904.978,857.842,826.9492,824.8044,774.772]},{"component":"SERIALIZATION","iterations":10000000,"library":{"id":"fc5220cb-3ca8-5528-84ff-663895a492cd","name":"Chr.Avro"},"times":[1292.9879,1350.6304,1443.6184,1231.5998,1432.4832]},{"component":"DESERIALIZATION","iterations":10000000,"library":{"id":"fc5220cb-3ca8-5528-84ff-663895a492cd","name":"Chr.Avro"},"times":[704.4078,807.1204,709.4385,717.0726,711.1116]}]},{"id":"c247632f-767d-5039-a2cd-26339c7b39b8","name":"record (generic)","results":[{"component":"SERIALIZATION","iterations":1000000,"library":{"id":"66e268f2-4d8f-59f4-872d-58609fb3bbe5","name":"Confluent.Apache.Avro"},"times":[440.3032,404.2775,373.6277,386.5259,367.1485]},{"component":"DESERIALIZATION","iterations":1000000,"library":{"id":"66e268f2-4d8f-59f4-872d-58609fb3bbe5","name":"Confluent.Apache.Avro"},"times":[728.3677,635.3598,640.2999,633.1287,631.74]}]},{"id":"b6664ef7-cf60-557d-82e6-9d69978e2e1a","name":"record (specific)","results":[{"component":"SERIALIZATION","iterations":1000000,"library":{"id":"66e268f2-4d8f-59f4-872d-58609fb3bbe5","name":"Confluent.Apache.Avro"},"times":[295.9632,270.9443,272.4297,274.234,281.3622]},{"component":"DESERIALIZATION","iterations":1000000,"library":{"id":"66e268f2-4d8f-59f4-872d-58609fb3bbe5","name":"Confluent.Apache.Avro"},"times":[331.6185,296.1289,297.9878,348.6266,297.0479]}]},{"id":"8ef83687-c3fd-5de3-81d1-caa50220475d","name":"record","results":[{"component":"SERIALIZATION","iterations":1000000,"library":{"id":"fc5220cb-3ca8-5528-84ff-663895a492cd","name":"Chr.Avro"},"times":[482.8016,465.4039,463.9419,480.688,525.4234]},{"component":"DESERIALIZATION","iterations":1000000,"library":{"id":"fc5220cb-3ca8-5528-84ff-663895a492cd","name":"Chr.Avro"},"times":[159.3841,160.7779,161.2991,190.5851,169.3651]}]}]},"site":{"siteMetadata":{"githubUrl":"https://github.com/ch-robinson/dotnet-avro","projectName":"Chr.Avro"}}}}